tronkeep/__init__.py
tronkeep/main.py
tronkeep-0.0.1.dist-info/licenses/LICENSE.txt
tronkeep-0.0.1.dist-info/METADATA
tronkeep-0.0.1.dist-info/WHEEL
tronkeep-0.0.1.dist-info/top_level.txt
tronkeep-0.0.1.dist-info/RECORD
