Metadata-Version: 2.4
Name: tronkeep
Version: 0.0.1
Summary: tronkeep library for Python
Author: somtron
Author-email: weekly.crayfish.vdpt@rapidletter.net
License: MIT
Project-URL: Source Repository, https://github.com
License-File: LICENSE.txt
Requires-Dist: requests
Dynamic: author
Dynamic: author-email
Dynamic: description
Dynamic: description-content-type
Dynamic: license
Dynamic: license-file
Dynamic: project-url
Dynamic: requires-dist
Dynamic: summary
